secretflow/__init__.py
secretflow/data/__init__.py
secretflow/data/base.py
secretflow/data/math_utils.py
secretflow/data/ndarray.py
secretflow/data/split.py
secretflow/data/horizontal/__init__.py
secretflow/data/horizontal/dataframe.py
secretflow/data/horizontal/io.py
secretflow/data/horizontal/sampler.py
secretflow/data/io/__init__.py
secretflow/data/io/oss.py
secretflow/data/io/util.py
secretflow/data/mix/__init__.py
secretflow/data/mix/dataframe.py
secretflow/data/vertical/__init__.py
secretflow/data/vertical/dataframe.py
secretflow/data/vertical/io.py
secretflow/device/__init__.py
secretflow/device/driver.py
secretflow/device/link.py
secretflow/device/proxy.py
secretflow/device/device/__init__.py
secretflow/device/device/base.py
secretflow/device/device/heu.py
secretflow/device/device/heu_object.py
secretflow/device/device/pyu.py
secretflow/device/device/register.py
secretflow/device/device/spu.py
secretflow/device/device/type_traits.py
secretflow/device/kernels/__init__.py
secretflow/device/kernels/heu.py
secretflow/device/kernels/pyu.py
secretflow/device/kernels/spu.py
secretflow/distributed/__init__.py
secretflow/distributed/primitive.py
secretflow/ml/__init__.py
secretflow/ml/boost/__init__.py
secretflow/ml/boost/homo_boost/__init__.py
secretflow/ml/boost/homo_boost/homo_booster.py
secretflow/ml/boost/homo_boost/homo_booster_worker.py
secretflow/ml/boost/homo_boost/homo_decision_tree.py
secretflow/ml/boost/homo_boost/tree_param.py
secretflow/ml/boost/homo_boost/boost_core/__init__.py
secretflow/ml/boost/homo_boost/boost_core/callback.py
secretflow/ml/boost/homo_boost/boost_core/core.py
secretflow/ml/boost/homo_boost/boost_core/training.py
secretflow/ml/boost/homo_boost/tree_core/__init__.py
secretflow/ml/boost/homo_boost/tree_core/criterion.py
secretflow/ml/boost/homo_boost/tree_core/decision_tree.py
secretflow/ml/boost/homo_boost/tree_core/feature_histogram.py
secretflow/ml/boost/homo_boost/tree_core/feature_importance.py
secretflow-0.7.18.dist-info/LICENSE
secretflow-0.7.18.dist-info/METADATA
secretflow-0.7.18.dist-info/WHEEL
secretflow-0.7.18.dist-info/top_level.txt
secretflow-0.7.18.dist-info/RECORD
