Metadata-Version: 2.1
Name: secretflow
Version: 0.7.18
Summary: Secret Flow
Home-page: https://github.com/secretflow/secretflow
Author: SCI Center
Author-email: secretflow-contact@service.alipay.com
License: Apache 2.0
Platform: UNKNOWN
Requires-Dist: numpy (>=1.22.0)
Requires-Dist: protobuf (==3.19.4)
Requires-Dist: jax
Requires-Dist: jaxlib
Requires-Dist: tensorflow-datasets
Requires-Dist: networkx (~=2.8)
Requires-Dist: tf2onnx (>=1.13.0)
Requires-Dist: secretflow-rayfed (==0.1.0b1)
Requires-Dist: pandas
Requires-Dist: pyarrow
Requires-Dist: sparse
Requires-Dist: scikit-learn (==1.1.3)
Requires-Dist: torch (==1.10.1)
Requires-Dist: torchvision (==0.11.2)
Requires-Dist: torchmetrics (==0.9.2)
Requires-Dist: s3fs (==2022.1.0)
Requires-Dist: xgboost (==1.5.2)
Requires-Dist: validator.py (==1.3.0)
Requires-Dist: tqdm
Requires-Dist: loguru
Requires-Dist: statsmodels (==0.13.2)
Requires-Dist: matplotlib
Requires-Dist: multiprocess
Requires-Dist: cachetools
Requires-Dist: psutil
Requires-Dist: coverage
Requires-Dist: unittest-xml-reporting
Requires-Dist: spu (==0.3.1b9)
Requires-Dist: sf-heu (==0.3.2b1)
Requires-Dist: tensorflow (==2.10.0) ; platform_machine != "arm64"
Requires-Dist: tensorflow-macos (==2.10.0) ; platform_machine == "arm64" and platform_system == "Darwin"
Provides-Extra: dev
Requires-Dist: pylint ; extra == 'dev'
